Blauwal3_ImageAnalytics-0.12.4-py3.10-nspkg.pth
orangecontrib/imageanalytics/__init__.py
orangecontrib/imageanalytics/i18n_config.py
orangecontrib/imageanalytics/image_embedder.py
orangecontrib/imageanalytics/image_grid.py
orangecontrib/imageanalytics/import_images.py
orangecontrib/imageanalytics/local_embedder.py
orangecontrib/imageanalytics/server_embedder.py
orangecontrib/imageanalytics/squeezenet_model.py
orangecontrib/imageanalytics/locale/imganlytic.de.yml
orangecontrib/imageanalytics/locale/imganlytic.en.yml
orangecontrib/imageanalytics/locale/imganlytic.zh.yml
orangecontrib/imageanalytics/tests/__init__.py
orangecontrib/imageanalytics/tests/test_image_embedder.py
orangecontrib/imageanalytics/tests/test_image_grid.py
orangecontrib/imageanalytics/tests/test_import_images.py
orangecontrib/imageanalytics/tests/test_squeezenet_model.py
orangecontrib/imageanalytics/tests/test_images/example_image_0.jpg
orangecontrib/imageanalytics/tests/test_images/example_image_1.tiff
orangecontrib/imageanalytics/tests/test_images/example_image_2.bmp
orangecontrib/imageanalytics/tests/test_images/example_image_2.gif
orangecontrib/imageanalytics/tests/test_images/example_image_2.jpeg
orangecontrib/imageanalytics/tests/test_images/example_image_2.jpg
orangecontrib/imageanalytics/tests/test_images/example_image_2.pbm
orangecontrib/imageanalytics/tests/test_images/example_image_2.pgm
orangecontrib/imageanalytics/tests/test_images/example_image_2.png
orangecontrib/imageanalytics/tests/test_images/example_image_2.pnm
orangecontrib/imageanalytics/tests/test_images/example_image_2.ppm
orangecontrib/imageanalytics/tests/test_images/example_image_2.tif
orangecontrib/imageanalytics/tests/test_images/example_image_2.tiff
orangecontrib/imageanalytics/tests/test_images/example_image_2.xbm
orangecontrib/imageanalytics/tests/test_images/example_image_2.xpm
orangecontrib/imageanalytics/tests/test_images/example_image_3.svg
orangecontrib/imageanalytics/tests/test_images/img/example_image_a.jpg
Blauwal3_ImageAnalytics-0.12.4.dist-info/LICENSE.txt
Blauwal3_ImageAnalytics-0.12.4.dist-info/METADATA
Blauwal3_ImageAnalytics-0.12.4.dist-info/WHEEL
Blauwal3_ImageAnalytics-0.12.4.dist-info/entry_points.txt
Blauwal3_ImageAnalytics-0.12.4.dist-info/namespace_packages.txt
Blauwal3_ImageAnalytics-0.12.4.dist-info/top_level.txt
Blauwal3_ImageAnalytics-0.12.4.dist-info/RECORD
